{
  "expectations": [
    {
      "id": "69faa130-0b84-46b8-a586-73b812e49d5f",
      "kwargs": {
        "min_value": 0,
        "strict_min": true
      },
      "meta": {
        "dimension": "completeness",
        "name": "row_count_expectation",
        "severity": "critical"
      },
      "severity": "critical",
      "type": "expect_table_row_count_to_be_between"
    },
    {
      "id": "fe63909e-3c8f-42ba-b24d-81f634296307",
      "kwargs": {
        "min_value": 1.0
      },
      "meta": {
        "dimension": "schema",
        "name": "column_count_expectation",
        "severity": "critical"
      },
      "severity": "critical",
      "type": "expect_table_column_count_to_be_between"
    },
    {
      "id": "bf524318-a33a-41fc-a768-f8ca6904be16",
      "kwargs": {
        "column_set": [
          "created_at",
          "updated_at",
          "is_deleted",
          "inserted_date"
        ],
        "exact_match": false,
        "result_format": {
          "result_format": "COMPLETE"
        }
      },
      "meta": {
        "dimension": "schema",
        "name": "mandatory_column_expectation",
        "severity": "critical"
      },
      "severity": "critical",
      "type": "expect_table_columns_to_match_set"
    },
    {
      "id": "704b014d-ca46-49bd-8cf4-e4886e166ae1",
      "kwargs": {
        "column": "branchid",
        "result_format": {
          "result_format": "COMPLETE",
          "return_unexpected_rows": true
        }
      },
      "meta": {
        "dimension": "correctness",
        "name": "branchid-ExpectColumnValuesToNotHaveDoubleSpace",
        "severity": "critical"
      },
      "severity": "critical",
      "type": "expect_column_values_to_not_have_double_space"
    },
    {
      "id": "11969f74-004e-4fce-8449-8983ff123344",
      "kwargs": {
        "column": "branchid",
        "result_format": {
          "result_format": "COMPLETE",
          "return_unexpected_rows": true
        }
      },
      "meta": {
        "dimension": "completeness",
        "name": "branchid-ExpectColumnValuesToNotBeNull",
        "severity": "critical"
      },
      "severity": "critical",
      "type": "expect_column_values_to_not_be_null"
    },
    {
      "id": "28721614-4af7-40aa-a79b-f9a2b9a386ad",
      "kwargs": {
        "column": "branchfullname",
        "result_format": {
          "result_format": "COMPLETE",
          "return_unexpected_rows": true
        }
      },
      "meta": {
        "dimension": "correctness",
        "name": "branchfullname-ExpectColumnValuesToNotHaveDoubleSpace",
        "severity": "critical"
      },
      "severity": "critical",
      "type": "expect_column_values_to_not_have_double_space"
    },
    {
      "id": "daae8286-5614-4872-8a44-48d45395cd72",
      "kwargs": {
        "column": "branchfullname",
        "result_format": {
          "result_format": "COMPLETE",
          "return_unexpected_rows": true
        }
      },
      "meta": {
        "dimension": "completeness",
        "name": "branchfullname-ExpectColumnValuesToNotBeNull",
        "severity": "critical"
      },
      "severity": "critical",
      "type": "expect_column_values_to_not_be_null"
    },
    {
      "id": "5385f205-7e4e-4e6d-8a37-2a4454f76364",
      "kwargs": {
        "column": "branchfullname",
        "result_format": {
          "result_format": "COMPLETE",
          "return_unexpected_rows": true
        }
      },
      "meta": {
        "dimension": "correctness",
        "name": "branchfullname-ExpectColumnValuesToNotContainSpecialCharacters",
        "severity": "critical"
      },
      "severity": "critical",
      "type": "expect_column_values_to_not_contain_special_characters"
    },
    {
      "id": "09385b4c-9497-4d72-b490-486e0338a37f",
      "kwargs": {
        "column": "applicationid",
        "result_format": {
          "result_format": "COMPLETE",
          "return_unexpected_rows": true
        }
      },
      "meta": {
        "dimension": "correctness",
        "name": "applicationid-ExpectColumnValuesToNotHaveDoubleSpace",
        "severity": "critical"
      },
      "severity": "critical",
      "type": "expect_column_values_to_not_have_double_space"
    },
    {
      "id": "9c2780b1-248c-40e4-b1a0-27a7850bb6d6",
      "kwargs": {
        "column": "applicationid",
        "result_format": {
          "result_format": "COMPLETE",
          "return_unexpected_rows": true
        }
      },
      "meta": {
        "dimension": "completeness",
        "name": "applicationid-ExpectColumnValuesToNotBeNull",
        "severity": "critical"
      },
      "severity": "critical",
      "type": "expect_column_values_to_not_be_null"
    },
    {
      "id": "c8b3c760-fc9e-4f1c-b4f9-7444eaf6a3a2",
      "kwargs": {
        "column": "agreementno",
        "result_format": {
          "result_format": "COMPLETE",
          "return_unexpected_rows": true
        }
      },
      "meta": {
        "dimension": "correctness",
        "name": "agreementno-ExpectColumnValuesToNotHaveDoubleSpace",
        "severity": "critical"
      },
      "severity": "critical",
      "type": "expect_column_values_to_not_have_double_space"
    },
    {
      "id": "8547ac31-94cd-40f8-a4ed-5c23b0469cbb",
      "kwargs": {
        "column": "agreementno",
        "result_format": {
          "result_format": "COMPLETE",
          "return_unexpected_rows": true
        }
      },
      "meta": {
        "dimension": "completeness",
        "name": "agreementno-ExpectColumnValuesToNotBeNull",
        "severity": "critical"
      },
      "severity": "critical",
      "type": "expect_column_values_to_not_be_null"
    },
    {
      "id": "672e8214-e2a5-4bf1-93a7-ab1a5c125b46",
      "kwargs": {
        "column": "name",
        "result_format": {
          "result_format": "COMPLETE",
          "return_unexpected_rows": true
        }
      },
      "meta": {
        "dimension": "correctness",
        "name": "name-ExpectColumnValuesToNotHaveDoubleSpace",
        "severity": "critical"
      },
      "severity": "critical",
      "type": "expect_column_values_to_not_have_double_space"
    },
    {
      "id": "4508803e-40b9-4d07-888b-b43e73c984cc",
      "kwargs": {
        "column": "name",
        "result_format": {
          "result_format": "COMPLETE",
          "return_unexpected_rows": true
        }
      },
      "meta": {
        "dimension": "completeness",
        "name": "name-ExpectColumnValuesToNotBeNull",
        "severity": "critical"
      },
      "severity": "critical",
      "type": "expect_column_values_to_not_be_null"
    },
    {
      "id": "1b71004f-c77a-4c6e-ba34-e6d6da8cc0f6",
      "kwargs": {
        "column": "name",
        "result_format": {
          "result_format": "COMPLETE",
          "return_unexpected_rows": true
        }
      },
      "meta": {
        "dimension": "correctness",
        "name": "name-ExpectColumnValuesToNotContainSpecialCharacters",
        "severity": "critical"
      },
      "severity": "critical",
      "type": "expect_column_values_to_not_contain_special_characters"
    },
    {
      "id": "7c804db4-56ed-4c9c-b5e3-f9839aaf9f29",
      "kwargs": {
        "column": "gender",
        "result_format": {
          "result_format": "COMPLETE",
          "return_unexpected_rows": true
        }
      },
      "meta": {
        "dimension": "correctness",
        "name": "gender-ExpectColumnValuesToNotHaveDoubleSpace",
        "severity": "critical"
      },
      "severity": "critical",
      "type": "expect_column_values_to_not_have_double_space"
    },
    {
      "id": "71f59e70-bbc1-46b0-88fb-ef332ecc455e",
      "kwargs": {
        "column": "gender",
        "result_format": {
          "result_format": "COMPLETE",
          "return_unexpected_rows": true
        }
      },
      "meta": {
        "dimension": "completeness",
        "name": "gender-ExpectColumnValuesToNotBeNull",
        "severity": "critical"
      },
      "severity": "critical",
      "type": "expect_column_values_to_not_be_null"
    },
    {
      "id": "dad585c9-f066-40e6-9e96-565e5bf496e8",
      "kwargs": {
        "column": "gender",
        "result_format": {
          "result_format": "COMPLETE",
          "return_unexpected_rows": true
        },
        "value_set": [
          "F",
          "M",
          "Female",
          "Male"
        ]
      },
      "meta": {
        "dimension": "correctness",
        "name": "gender-ExpectColumnValuesToBeInSet",
        "severity": "warning"
      },
      "severity": "critical",
      "type": "expect_column_values_to_be_in_set"
    },
    {
      "id": "6e16957f-3a0e-4e2a-b9d4-a72f50776fae",
      "kwargs": {
        "column": "maritalstatus",
        "result_format": {
          "result_format": "COMPLETE",
          "return_unexpected_rows": true
        }
      },
      "meta": {
        "dimension": "correctness",
        "name": "maritalstatus-ExpectColumnValuesToNotHaveDoubleSpace",
        "severity": "critical"
      },
      "severity": "critical",
      "type": "expect_column_values_to_not_have_double_space"
    },
    {
      "id": "4092875e-7a79-4d12-acc1-b20142dc898c",
      "kwargs": {
        "column": "maritalstatus",
        "result_format": {
          "result_format": "COMPLETE",
          "return_unexpected_rows": true
        }
      },
      "meta": {
        "dimension": "completeness",
        "name": "maritalstatus-ExpectColumnValuesToNotBeNull",
        "severity": "critical"
      },
      "severity": "critical",
      "type": "expect_column_values_to_not_be_null"
    },
    {
      "id": "73f75e22-7e0c-43fd-905d-54384789b38a",
      "kwargs": {
        "column": "maritalstatus",
        "result_format": {
          "result_format": "COMPLETE",
          "return_unexpected_rows": true
        },
        "value_set": [
          "Single",
          "Maried",
          "Widdow",
          "Widdower",
          "Divorce"
        ]
      },
      "meta": {
        "dimension": "correctness",
        "name": "maritalstatus-ExpectColumnValuesToBeInSet",
        "severity": "warning"
      },
      "severity": "critical",
      "type": "expect_column_values_to_be_in_set"
    },
    {
      "id": "f2f4a4cd-4e57-4d04-b069-642248b886cf",
      "kwargs": {
        "column": "spousename",
        "result_format": {
          "result_format": "COMPLETE",
          "return_unexpected_rows": true
        }
      },
      "meta": {
        "dimension": "correctness",
        "name": "spousename-ExpectColumnValuesToNotHaveDoubleSpace",
        "severity": "critical"
      },
      "severity": "critical",
      "type": "expect_column_values_to_not_have_double_space"
    },
    {
      "id": "04ff1e00-77b2-4be9-82af-cb57c60b461f",
      "kwargs": {
        "column": "spousename",
        "result_format": {
          "result_format": "COMPLETE",
          "return_unexpected_rows": true
        }
      },
      "meta": {
        "dimension": "completeness",
        "name": "spousename-ExpectColumnValuesToNotBeNull",
        "severity": "critical"
      },
      "severity": "critical",
      "type": "expect_column_values_to_not_be_null"
    },
    {
      "id": "e2c24978-b231-48f6-a1be-90f9697b57f7",
      "kwargs": {
        "column": "spousename",
        "result_format": {
          "result_format": "COMPLETE",
          "return_unexpected_rows": true
        }
      },
      "meta": {
        "dimension": "correctness",
        "name": "spousename-ExpectColumnValuesToNotContainSpecialCharacters",
        "severity": "critical"
      },
      "severity": "critical",
      "type": "expect_column_values_to_not_contain_special_characters"
    },
    {
      "id": "54abcd79-b7db-4313-ba1e-9051eaf3c716",
      "kwargs": {
        "column": "birthplace",
        "result_format": {
          "result_format": "COMPLETE",
          "return_unexpected_rows": true
        }
      },
      "meta": {
        "dimension": "correctness",
        "name": "birthplace-ExpectColumnValuesToNotHaveDoubleSpace",
        "severity": "critical"
      },
      "severity": "critical",
      "type": "expect_column_values_to_not_have_double_space"
    },
    {
      "id": "9318311e-30c4-4f42-a8e2-739908fe6fdb",
      "kwargs": {
        "column": "birthplace",
        "result_format": {
          "result_format": "COMPLETE",
          "return_unexpected_rows": true
        }
      },
      "meta": {
        "dimension": "completeness",
        "name": "birthplace-ExpectColumnValuesToNotBeNull",
        "severity": "critical"
      },
      "severity": "critical",
      "type": "expect_column_values_to_not_be_null"
    },
    {
      "id": "0c6ee8f4-8254-4655-a659-731d7a9d8764",
      "kwargs": {
        "column": "birthdate",
        "result_format": {
          "result_format": "COMPLETE",
          "return_unexpected_rows": true
        }
      },
      "meta": {
        "dimension": "correctness",
        "name": "birthdate-ExpectColumnValuesToNotHaveDoubleSpace",
        "severity": "critical"
      },
      "severity": "critical",
      "type": "expect_column_values_to_not_have_double_space"
    },
    {
      "id": "509b4eee-dd43-4464-964d-4d159017e301",
      "kwargs": {
        "column": "birthdate",
        "result_format": {
          "result_format": "COMPLETE",
          "return_unexpected_rows": true
        }
      },
      "meta": {
        "dimension": "completeness",
        "name": "birthdate-ExpectColumnValuesToNotBeNull",
        "severity": "critical"
      },
      "severity": "critical",
      "type": "expect_column_values_to_not_be_null"
    },
    {
      "id": "46582b08-626b-464b-8b11-9c16be5eccc7",
      "kwargs": {
        "column": "surgatemothername",
        "result_format": {
          "result_format": "COMPLETE",
          "return_unexpected_rows": true
        }
      },
      "meta": {
        "dimension": "correctness",
        "name": "surgatemothername-ExpectColumnValuesToNotHaveDoubleSpace",
        "severity": "critical"
      },
      "severity": "critical",
      "type": "expect_column_values_to_not_have_double_space"
    },
    {
      "id": "fbdb64d1-dd80-4122-b000-18bd03afd294",
      "kwargs": {
        "column": "surgatemothername",
        "result_format": {
          "result_format": "COMPLETE",
          "return_unexpected_rows": true
        }
      },
      "meta": {
        "dimension": "completeness",
        "name": "surgatemothername-ExpectColumnValuesToNotBeNull",
        "severity": "critical"
      },
      "severity": "critical",
      "type": "expect_column_values_to_not_be_null"
    },
    {
      "id": "e8ab2e78-8f05-44f1-ba8f-834ad37c01ef",
      "kwargs": {
        "column": "surgatemothername",
        "result_format": {
          "result_format": "COMPLETE",
          "return_unexpected_rows": true
        }
      },
      "meta": {
        "dimension": "correctness",
        "name": "surgatemothername-ExpectColumnValuesToNotContainSpecialCharacters",
        "severity": "critical"
      },
      "severity": "critical",
      "type": "expect_column_values_to_not_contain_special_characters"
    },
    {
      "id": "fa35eb2d-16a8-48e8-866f-8a94b215ffdb",
      "kwargs": {
        "column": "profession",
        "result_format": {
          "result_format": "COMPLETE",
          "return_unexpected_rows": true
        }
      },
      "meta": {
        "dimension": "correctness",
        "name": "profession-ExpectColumnValuesToNotHaveDoubleSpace",
        "severity": "critical"
      },
      "severity": "critical",
      "type": "expect_column_values_to_not_have_double_space"
    },
    {
      "id": "3d5fa45a-095e-4cfa-87a5-c7fb43148d03",
      "kwargs": {
        "column": "profession",
        "result_format": {
          "result_format": "COMPLETE",
          "return_unexpected_rows": true
        }
      },
      "meta": {
        "dimension": "completeness",
        "name": "profession-ExpectColumnValuesToNotBeNull",
        "severity": "critical"
      },
      "severity": "critical",
      "type": "expect_column_values_to_not_be_null"
    },
    {
      "id": "81a0a2c2-5f39-491e-ab90-8f88a139cb21",
      "kwargs": {
        "column": "companyname",
        "result_format": {
          "result_format": "COMPLETE",
          "return_unexpected_rows": true
        }
      },
      "meta": {
        "dimension": "correctness",
        "name": "companyname-ExpectColumnValuesToNotHaveDoubleSpace",
        "severity": "critical"
      },
      "severity": "critical",
      "type": "expect_column_values_to_not_have_double_space"
    },
    {
      "id": "f28d3ce8-3d0f-4172-9a90-a5b84b6f486d",
      "kwargs": {
        "column": "companyname",
        "result_format": {
          "result_format": "COMPLETE",
          "return_unexpected_rows": true
        }
      },
      "meta": {
        "dimension": "completeness",
        "name": "companyname-ExpectColumnValuesToNotBeNull",
        "severity": "critical"
      },
      "severity": "critical",
      "type": "expect_column_values_to_not_be_null"
    },
    {
      "id": "47764c62-28a2-47ee-8018-68d47302fc37",
      "kwargs": {
        "column": "companyname",
        "result_format": {
          "result_format": "COMPLETE",
          "return_unexpected_rows": true
        }
      },
      "meta": {
        "dimension": "correctness",
        "name": "companyname-ExpectColumnValuesToNotContainSpecialCharacters",
        "severity": "critical"
      },
      "severity": "critical",
      "type": "expect_column_values_to_not_contain_special_characters"
    },
    {
      "id": "2c1f8b43-d600-416f-bf49-76ea756dadeb",
      "kwargs": {
        "column": "assetdescription",
        "result_format": {
          "result_format": "COMPLETE",
          "return_unexpected_rows": true
        }
      },
      "meta": {
        "dimension": "correctness",
        "name": "assetdescription-ExpectColumnValuesToNotHaveDoubleSpace",
        "severity": "critical"
      },
      "severity": "critical",
      "type": "expect_column_values_to_not_have_double_space"
    },
    {
      "id": "685e6806-e891-4708-bfcb-0e85e96270da",
      "kwargs": {
        "column": "assetdescription",
        "result_format": {
          "result_format": "COMPLETE",
          "return_unexpected_rows": true
        }
      },
      "meta": {
        "dimension": "completeness",
        "name": "assetdescription-ExpectColumnValuesToNotBeNull",
        "severity": "critical"
      },
      "severity": "critical",
      "type": "expect_column_values_to_not_be_null"
    },
    {
      "id": "728bf16a-a25f-4251-be1d-25eb368fd91f",
      "kwargs": {
        "column": "licenseplate",
        "result_format": {
          "result_format": "COMPLETE",
          "return_unexpected_rows": true
        }
      },
      "meta": {
        "dimension": "correctness",
        "name": "licenseplate-ExpectColumnValuesToNotHaveDoubleSpace",
        "severity": "critical"
      },
      "severity": "critical",
      "type": "expect_column_values_to_not_have_double_space"
    },
    {
      "id": "7512bf7e-ac0d-4ee7-b6c2-66051863f4dc",
      "kwargs": {
        "column": "licenseplate",
        "result_format": {
          "result_format": "COMPLETE",
          "return_unexpected_rows": true
        }
      },
      "meta": {
        "dimension": "completeness",
        "name": "licenseplate-ExpectColumnValuesToNotBeNull",
        "severity": "critical"
      },
      "severity": "critical",
      "type": "expect_column_values_to_not_be_null"
    },
    {
      "id": "25b7fdb3-d93b-4d2c-8354-a0da103b0fa5",
      "kwargs": {
        "column": "licenseplate",
        "regex": "^[A-Z]{1,2}\\s?[0-9]{1,4}\\s?[A-Z]{0,3}$",
        "result_format": {
          "result_format": "COMPLETE",
          "return_unexpected_rows": true
        }
      },
      "meta": {
        "dimension": "correctness",
        "name": "licenseplate-ExpectColumnValuesToMatchRegex",
        "severity": "critical"
      },
      "severity": "critical",
      "type": "expect_column_values_to_match_regex"
    },
    {
      "id": "64acafbc-b8d6-416a-b0a6-eadb0bc6279d",
      "kwargs": {
        "column": "color",
        "result_format": {
          "result_format": "COMPLETE",
          "return_unexpected_rows": true
        }
      },
      "meta": {
        "dimension": "correctness",
        "name": "color-ExpectColumnValuesToNotHaveDoubleSpace",
        "severity": "critical"
      },
      "severity": "critical",
      "type": "expect_column_values_to_not_have_double_space"
    },
    {
      "id": "29536e0b-6110-40fe-ab5e-c1c017594bba",
      "kwargs": {
        "column": "color",
        "result_format": {
          "result_format": "COMPLETE",
          "return_unexpected_rows": true
        }
      },
      "meta": {
        "dimension": "completeness",
        "name": "color-ExpectColumnValuesToNotBeNull",
        "severity": "critical"
      },
      "severity": "critical",
      "type": "expect_column_values_to_not_be_null"
    },
    {
      "id": "9c21cba9-e999-4586-b2ea-321f1ab9ccac",
      "kwargs": {
        "column": "manufacturingyear",
        "min_value": 0.0,
        "result_format": {
          "result_format": "COMPLETE",
          "return_unexpected_rows": true
        }
      },
      "meta": {
        "dimension": "correctness",
        "name": "manufacturingyear-ExpectColumnValuesToBeBetween",
        "severity": "warning"
      },
      "severity": "critical",
      "type": "expect_column_values_to_be_between"
    },
    {
      "id": "131329fa-e1a7-41f8-8483-5f15f189f29d",
      "kwargs": {
        "column": "manufacturingyear",
        "result_format": {
          "result_format": "COMPLETE",
          "return_unexpected_rows": true
        }
      },
      "meta": {
        "dimension": "completeness",
        "name": "manufacturingyear-ExpectColumnValuesToNotBeNull",
        "severity": "critical"
      },
      "severity": "critical",
      "type": "expect_column_values_to_not_be_null"
    },
    {
      "id": "19c33843-2302-4ae7-b3b8-5bdbb0bb2962",
      "kwargs": {
        "column": "manufacturingyear",
        "min_value": 1901.0,
        "result_format": {
          "result_format": "COMPLETE",
          "return_unexpected_rows": true
        }
      },
      "meta": {
        "dimension": "correctness",
        "name": "manufacturingyear-ExpectColumnValuesToBeBetween",
        "severity": "critical"
      },
      "severity": "critical",
      "type": "expect_column_values_to_be_between"
    },
    {
      "id": "358a392b-37a3-4901-9f96-43ef19d10981",
      "kwargs": {
        "column": "nextinstallmentnumber",
        "min_value": 0.0,
        "result_format": {
          "result_format": "COMPLETE",
          "return_unexpected_rows": true
        }
      },
      "meta": {
        "dimension": "correctness",
        "name": "nextinstallmentnumber-ExpectColumnValuesToBeBetween",
        "severity": "warning"
      },
      "severity": "critical",
      "type": "expect_column_values_to_be_between"
    },
    {
      "id": "17a3f382-385b-401a-8760-50c98505d2ec",
      "kwargs": {
        "column": "nextinstallmentnumber",
        "result_format": {
          "result_format": "COMPLETE",
          "return_unexpected_rows": true
        }
      },
      "meta": {
        "dimension": "completeness",
        "name": "nextinstallmentnumber-ExpectColumnValuesToNotBeNull",
        "severity": "critical"
      },
      "severity": "critical",
      "type": "expect_column_values_to_not_be_null"
    },
    {
      "id": "a2d6142b-7040-40f5-97fc-31e54fbad270",
      "kwargs": {
        "column": "agreementdate",
        "result_format": {
          "result_format": "COMPLETE",
          "return_unexpected_rows": true
        }
      },
      "meta": {
        "dimension": "correctness",
        "name": "agreementdate-ExpectColumnValuesToNotHaveDoubleSpace",
        "severity": "critical"
      },
      "severity": "critical",
      "type": "expect_column_values_to_not_have_double_space"
    },
    {
      "id": "ba44f3fd-4827-420f-978d-ebc8f84ec1f1",
      "kwargs": {
        "column": "agreementdate",
        "result_format": {
          "result_format": "COMPLETE",
          "return_unexpected_rows": true
        }
      },
      "meta": {
        "dimension": "completeness",
        "name": "agreementdate-ExpectColumnValuesToNotBeNull",
        "severity": "critical"
      },
      "severity": "critical",
      "type": "expect_column_values_to_not_be_null"
    },
    {
      "id": "6069d800-2b7b-49f0-b9e0-654748b8a269",
      "kwargs": {
        "column": "effectivedate",
        "result_format": {
          "result_format": "COMPLETE",
          "return_unexpected_rows": true
        }
      },
      "meta": {
        "dimension": "correctness",
        "name": "effectivedate-ExpectColumnValuesToNotHaveDoubleSpace",
        "severity": "critical"
      },
      "severity": "critical",
      "type": "expect_column_values_to_not_have_double_space"
    },
    {
      "id": "0801be13-edb3-472f-a979-a20d700dcec9",
      "kwargs": {
        "column": "effectivedate",
        "result_format": {
          "result_format": "COMPLETE",
          "return_unexpected_rows": true
        }
      },
      "meta": {
        "dimension": "completeness",
        "name": "effectivedate-ExpectColumnValuesToNotBeNull",
        "severity": "critical"
      },
      "severity": "critical",
      "type": "expect_column_values_to_not_be_null"
    },
    {
      "id": "0c3def62-e49f-421f-88ef-adebe0d81cd9",
      "kwargs": {
        "column": "maturitydate",
        "result_format": {
          "result_format": "COMPLETE",
          "return_unexpected_rows": true
        }
      },
      "meta": {
        "dimension": "correctness",
        "name": "maturitydate-ExpectColumnValuesToNotHaveDoubleSpace",
        "severity": "critical"
      },
      "severity": "critical",
      "type": "expect_column_values_to_not_have_double_space"
    },
    {
      "id": "6b637725-519c-4c26-9314-83222e6e159f",
      "kwargs": {
        "column": "maturitydate",
        "result_format": {
          "result_format": "COMPLETE",
          "return_unexpected_rows": true
        }
      },
      "meta": {
        "dimension": "completeness",
        "name": "maturitydate-ExpectColumnValuesToNotBeNull",
        "severity": "critical"
      },
      "severity": "critical",
      "type": "expect_column_values_to_not_be_null"
    },
    {
      "id": "e55f50c8-a08b-4981-b436-ec354c59fad1",
      "kwargs": {
        "column": "duedate",
        "result_format": {
          "result_format": "COMPLETE",
          "return_unexpected_rows": true
        }
      },
      "meta": {
        "dimension": "correctness",
        "name": "duedate-ExpectColumnValuesToNotHaveDoubleSpace",
        "severity": "critical"
      },
      "severity": "critical",
      "type": "expect_column_values_to_not_have_double_space"
    },
    {
      "id": "4bd7ce04-d18a-4e66-b632-b0bb9756d213",
      "kwargs": {
        "column": "duedate",
        "result_format": {
          "result_format": "COMPLETE",
          "return_unexpected_rows": true
        }
      },
      "meta": {
        "dimension": "completeness",
        "name": "duedate-ExpectColumnValuesToNotBeNull",
        "severity": "critical"
      },
      "severity": "critical",
      "type": "expect_column_values_to_not_be_null"
    },
    {
      "id": "9e20a0bf-1593-417c-9061-712dbf5d4e7d",
      "kwargs": {
        "column": "tenor",
        "min_value": 0.0,
        "result_format": {
          "result_format": "COMPLETE",
          "return_unexpected_rows": true
        }
      },
      "meta": {
        "dimension": "correctness",
        "name": "tenor-ExpectColumnValuesToBeBetween",
        "severity": "warning"
      },
      "severity": "critical",
      "type": "expect_column_values_to_be_between"
    },
    {
      "id": "8b3c7858-78d7-4ea3-95ce-2de2a79aeba7",
      "kwargs": {
        "column": "tenor",
        "result_format": {
          "result_format": "COMPLETE",
          "return_unexpected_rows": true
        }
      },
      "meta": {
        "dimension": "completeness",
        "name": "tenor-ExpectColumnValuesToNotBeNull",
        "severity": "critical"
      },
      "severity": "critical",
      "type": "expect_column_values_to_not_be_null"
    },
    {
      "id": "c497f587-0328-4611-b550-0a5b57e10234",
      "kwargs": {
        "column": "productoffering",
        "result_format": {
          "result_format": "COMPLETE",
          "return_unexpected_rows": true
        }
      },
      "meta": {
        "dimension": "correctness",
        "name": "productoffering-ExpectColumnValuesToNotHaveDoubleSpace",
        "severity": "critical"
      },
      "severity": "critical",
      "type": "expect_column_values_to_not_have_double_space"
    },
    {
      "id": "a461216a-c4b1-4052-8b99-6777846ef989",
      "kwargs": {
        "column": "productoffering",
        "result_format": {
          "result_format": "COMPLETE",
          "return_unexpected_rows": true
        }
      },
      "meta": {
        "dimension": "completeness",
        "name": "productoffering-ExpectColumnValuesToNotBeNull",
        "severity": "critical"
      },
      "severity": "critical",
      "type": "expect_column_values_to_not_be_null"
    },
    {
      "id": "68c94715-ab3c-44fa-a312-218247b0d009",
      "kwargs": {
        "column": "firstinstallment",
        "result_format": {
          "result_format": "COMPLETE",
          "return_unexpected_rows": true
        }
      },
      "meta": {
        "dimension": "correctness",
        "name": "firstinstallment-ExpectColumnValuesToNotHaveDoubleSpace",
        "severity": "critical"
      },
      "severity": "critical",
      "type": "expect_column_values_to_not_have_double_space"
    },
    {
      "id": "fa80e379-0274-45f0-96c3-df7a2f01ce4e",
      "kwargs": {
        "column": "firstinstallment",
        "result_format": {
          "result_format": "COMPLETE",
          "return_unexpected_rows": true
        }
      },
      "meta": {
        "dimension": "completeness",
        "name": "firstinstallment-ExpectColumnValuesToNotBeNull",
        "severity": "critical"
      },
      "severity": "critical",
      "type": "expect_column_values_to_not_be_null"
    },
    {
      "id": "96fd8d17-7e6e-4efa-aa4a-5386305c0bdb",
      "kwargs": {
        "column": "firstinstallment",
        "result_format": {
          "result_format": "COMPLETE",
          "return_unexpected_rows": true
        },
        "value_set": [
          "AR",
          "AD",
          "ARREAR",
          "ADVANCE"
        ]
      },
      "meta": {
        "dimension": "correctness",
        "name": "firstinstallment-ExpectColumnValuesToBeInSet",
        "severity": "warning"
      },
      "severity": "critical",
      "type": "expect_column_values_to_be_in_set"
    },
    {
      "id": "46142c31-019e-402f-bcd4-3078c3e8a342",
      "kwargs": {
        "column": "graceperiodlatecharges",
        "min_value": 0.0,
        "result_format": {
          "result_format": "COMPLETE",
          "return_unexpected_rows": true
        }
      },
      "meta": {
        "dimension": "correctness",
        "name": "graceperiodlatecharges-ExpectColumnValuesToBeBetween",
        "severity": "warning"
      },
      "severity": "critical",
      "type": "expect_column_values_to_be_between"
    },
    {
      "id": "86cba653-629b-415e-9987-d6c29b1cebd9",
      "kwargs": {
        "column": "graceperiodlatecharges",
        "result_format": {
          "result_format": "COMPLETE",
          "return_unexpected_rows": true
        }
      },
      "meta": {
        "dimension": "completeness",
        "name": "graceperiodlatecharges-ExpectColumnValuesToNotBeNull",
        "severity": "critical"
      },
      "severity": "critical",
      "type": "expect_column_values_to_not_be_null"
    },
    {
      "id": "5311b9cf-c073-40a7-87d2-0742860e6497",
      "kwargs": {
        "column": "paymenthierarchy",
        "result_format": {
          "result_format": "COMPLETE",
          "return_unexpected_rows": true
        }
      },
      "meta": {
        "dimension": "correctness",
        "name": "paymenthierarchy-ExpectColumnValuesToNotHaveDoubleSpace",
        "severity": "critical"
      },
      "severity": "critical",
      "type": "expect_column_values_to_not_have_double_space"
    },
    {
      "id": "87f27f11-a278-48d9-9fc3-7f04cb8e3ea1",
      "kwargs": {
        "column": "paymenthierarchy",
        "result_format": {
          "result_format": "COMPLETE",
          "return_unexpected_rows": true
        }
      },
      "meta": {
        "dimension": "completeness",
        "name": "paymenthierarchy-ExpectColumnValuesToNotBeNull",
        "severity": "critical"
      },
      "severity": "critical",
      "type": "expect_column_values_to_not_be_null"
    },
    {
      "id": "01c4acc5-5e56-4dd9-9fa5-8df3507d40a2",
      "kwargs": {
        "column": "installmentreminder",
        "min_value": 0.0,
        "result_format": {
          "result_format": "COMPLETE",
          "return_unexpected_rows": true
        }
      },
      "meta": {
        "dimension": "correctness",
        "name": "installmentreminder-ExpectColumnValuesToBeBetween",
        "severity": "warning"
      },
      "severity": "critical",
      "type": "expect_column_values_to_be_between"
    },
    {
      "id": "ce9d19da-02d3-41f3-8e44-3fadcfc89773",
      "kwargs": {
        "column": "installmentreminder",
        "result_format": {
          "result_format": "COMPLETE",
          "return_unexpected_rows": true
        }
      },
      "meta": {
        "dimension": "completeness",
        "name": "installmentreminder-ExpectColumnValuesToNotBeNull",
        "severity": "critical"
      },
      "severity": "critical",
      "type": "expect_column_values_to_not_be_null"
    },
    {
      "id": "80656349-0318-4b9c-a2e8-39265029acda",
      "kwargs": {
        "column": "remindertype",
        "result_format": {
          "result_format": "COMPLETE",
          "return_unexpected_rows": true
        }
      },
      "meta": {
        "dimension": "correctness",
        "name": "remindertype-ExpectColumnValuesToNotHaveDoubleSpace",
        "severity": "critical"
      },
      "severity": "critical",
      "type": "expect_column_values_to_not_have_double_space"
    },
    {
      "id": "df2fc7da-42cd-4b6e-a74c-08f46b56ec56",
      "kwargs": {
        "column": "remindertype",
        "result_format": {
          "result_format": "COMPLETE",
          "return_unexpected_rows": true
        }
      },
      "meta": {
        "dimension": "completeness",
        "name": "remindertype-ExpectColumnValuesToNotBeNull",
        "severity": "critical"
      },
      "severity": "critical",
      "type": "expect_column_values_to_not_be_null"
    },
    {
      "id": "6605d557-bbff-4635-8512-1c7c90875fc6",
      "kwargs": {
        "column": "surveyorid1",
        "result_format": {
          "result_format": "COMPLETE",
          "return_unexpected_rows": true
        }
      },
      "meta": {
        "dimension": "correctness",
        "name": "surveyorid1-ExpectColumnValuesToNotHaveDoubleSpace",
        "severity": "critical"
      },
      "severity": "critical",
      "type": "expect_column_values_to_not_have_double_space"
    },
    {
      "id": "6c1f6622-50c5-4ae4-8673-e963e81d7125",
      "kwargs": {
        "column": "surveyorid1",
        "result_format": {
          "result_format": "COMPLETE",
          "return_unexpected_rows": true
        }
      },
      "meta": {
        "dimension": "completeness",
        "name": "surveyorid1-ExpectColumnValuesToNotBeNull",
        "severity": "critical"
      },
      "severity": "critical",
      "type": "expect_column_values_to_not_be_null"
    },
    {
      "id": "6b4ddcc7-2aea-47b4-ae3f-12cca9006eb9",
      "kwargs": {
        "column": "assetdocstatus",
        "result_format": {
          "result_format": "COMPLETE",
          "return_unexpected_rows": true
        }
      },
      "meta": {
        "dimension": "correctness",
        "name": "assetdocstatus-ExpectColumnValuesToNotHaveDoubleSpace",
        "severity": "critical"
      },
      "severity": "critical",
      "type": "expect_column_values_to_not_have_double_space"
    },
    {
      "id": "bd4d548d-2e0f-49c8-99bb-2f6e7f192a6b",
      "kwargs": {
        "column": "assetdocstatus",
        "result_format": {
          "result_format": "COMPLETE",
          "return_unexpected_rows": true
        }
      },
      "meta": {
        "dimension": "completeness",
        "name": "assetdocstatus-ExpectColumnValuesToNotBeNull",
        "severity": "critical"
      },
      "severity": "critical",
      "type": "expect_column_values_to_not_be_null"
    },
    {
      "id": "60a1b1fa-6468-40e4-bf79-cd231998dbf8",
      "kwargs": {
        "column": "doclocation",
        "result_format": {
          "result_format": "COMPLETE",
          "return_unexpected_rows": true
        }
      },
      "meta": {
        "dimension": "correctness",
        "name": "doclocation-ExpectColumnValuesToNotHaveDoubleSpace",
        "severity": "critical"
      },
      "severity": "critical",
      "type": "expect_column_values_to_not_have_double_space"
    },
    {
      "id": "48908568-0e56-4d71-bc2f-1e9e35fa986f",
      "kwargs": {
        "column": "doclocation",
        "result_format": {
          "result_format": "COMPLETE",
          "return_unexpected_rows": true
        }
      },
      "meta": {
        "dimension": "completeness",
        "name": "doclocation-ExpectColumnValuesToNotBeNull",
        "severity": "critical"
      },
      "severity": "critical",
      "type": "expect_column_values_to_not_be_null"
    },
    {
      "id": "6d0536ba-53ae-46bf-9629-168fc476191f",
      "kwargs": {
        "column": "branchlocation",
        "result_format": {
          "result_format": "COMPLETE",
          "return_unexpected_rows": true
        }
      },
      "meta": {
        "dimension": "correctness",
        "name": "branchlocation-ExpectColumnValuesToNotHaveDoubleSpace",
        "severity": "critical"
      },
      "severity": "critical",
      "type": "expect_column_values_to_not_have_double_space"
    },
    {
      "id": "9607a069-ba6e-4fbc-b15b-a2d602ca0817",
      "kwargs": {
        "column": "branchlocation",
        "result_format": {
          "result_format": "COMPLETE",
          "return_unexpected_rows": true
        }
      },
      "meta": {
        "dimension": "completeness",
        "name": "branchlocation-ExpectColumnValuesToNotBeNull",
        "severity": "critical"
      },
      "severity": "critical",
      "type": "expect_column_values_to_not_be_null"
    },
    {
      "id": "4c361e37-216d-4e38-8c01-58b72aad4316",
      "kwargs": {
        "column": "customerid",
        "result_format": {
          "result_format": "COMPLETE",
          "return_unexpected_rows": true
        }
      },
      "meta": {
        "dimension": "correctness",
        "name": "customerid-ExpectColumnValuesToNotHaveDoubleSpace",
        "severity": "critical"
      },
      "severity": "critical",
      "type": "expect_column_values_to_not_have_double_space"
    },
    {
      "id": "ad1bb669-4d4c-4697-957e-f155d478d34d",
      "kwargs": {
        "column": "customerid",
        "result_format": {
          "result_format": "COMPLETE",
          "return_unexpected_rows": true
        }
      },
      "meta": {
        "dimension": "completeness",
        "name": "customerid-ExpectColumnValuesToNotBeNull",
        "severity": "critical"
      },
      "severity": "critical",
      "type": "expect_column_values_to_not_be_null"
    },
    {
      "id": "c4e36867-e8c9-40ba-9c11-1dce269e856f",
      "kwargs": {
        "column": "residenceaddress",
        "result_format": {
          "result_format": "COMPLETE",
          "return_unexpected_rows": true
        }
      },
      "meta": {
        "dimension": "correctness",
        "name": "residenceaddress-ExpectColumnValuesToNotHaveDoubleSpace",
        "severity": "critical"
      },
      "severity": "critical",
      "type": "expect_column_values_to_not_have_double_space"
    },
    {
      "id": "e14fc256-86d7-4c11-86f2-bdba9306d3d3",
      "kwargs": {
        "column": "residenceaddress",
        "result_format": {
          "result_format": "COMPLETE",
          "return_unexpected_rows": true
        }
      },
      "meta": {
        "dimension": "completeness",
        "name": "residenceaddress-ExpectColumnValuesToNotBeNull",
        "severity": "critical"
      },
      "severity": "critical",
      "type": "expect_column_values_to_not_be_null"
    },
    {
      "id": "881ca430-3fe6-46c6-bac6-d9f1ca9a5c51",
      "kwargs": {
        "column": "installmentamount",
        "result_format": {
          "result_format": "COMPLETE",
          "return_unexpected_rows": true
        }
      },
      "meta": {
        "dimension": "correctness",
        "name": "installmentamount-ExpectColumnValuesToNotHaveDoubleSpace",
        "severity": "critical"
      },
      "severity": "critical",
      "type": "expect_column_values_to_not_have_double_space"
    },
    {
      "id": "e17f67b5-54e1-4bdb-9448-59b4136dc3d0",
      "kwargs": {
        "column": "installmentamount",
        "result_format": {
          "result_format": "COMPLETE",
          "return_unexpected_rows": true
        }
      },
      "meta": {
        "dimension": "completeness",
        "name": "installmentamount-ExpectColumnValuesToNotBeNull",
        "severity": "critical"
      },
      "severity": "critical",
      "type": "expect_column_values_to_not_be_null"
    },
    {
      "id": "385b7357-6cf6-45db-8e0e-678c3a9094a6",
      "kwargs": {
        "column": "contractprepaidamount",
        "result_format": {
          "result_format": "COMPLETE",
          "return_unexpected_rows": true
        }
      },
      "meta": {
        "dimension": "correctness",
        "name": "contractprepaidamount-ExpectColumnValuesToNotHaveDoubleSpace",
        "severity": "critical"
      },
      "severity": "critical",
      "type": "expect_column_values_to_not_have_double_space"
    },
    {
      "id": "64cc00ad-0378-48da-9ac1-e0d01ded5f38",
      "kwargs": {
        "column": "contractprepaidamount",
        "result_format": {
          "result_format": "COMPLETE",
          "return_unexpected_rows": true
        }
      },
      "meta": {
        "dimension": "completeness",
        "name": "contractprepaidamount-ExpectColumnValuesToNotBeNull",
        "severity": "critical"
      },
      "severity": "critical",
      "type": "expect_column_values_to_not_be_null"
    },
    {
      "id": "b8819915-51d7-4928-b291-eae327a137f7",
      "kwargs": {
        "column": "osinstallmentdue",
        "result_format": {
          "result_format": "COMPLETE",
          "return_unexpected_rows": true
        }
      },
      "meta": {
        "dimension": "correctness",
        "name": "osinstallmentdue-ExpectColumnValuesToNotHaveDoubleSpace",
        "severity": "critical"
      },
      "severity": "critical",
      "type": "expect_column_values_to_not_have_double_space"
    },
    {
      "id": "59eaf0af-e66d-431f-bcba-0cdd22cfa3f1",
      "kwargs": {
        "column": "osinstallmentdue",
        "result_format": {
          "result_format": "COMPLETE",
          "return_unexpected_rows": true
        }
      },
      "meta": {
        "dimension": "completeness",
        "name": "osinstallmentdue-ExpectColumnValuesToNotBeNull",
        "severity": "critical"
      },
      "severity": "critical",
      "type": "expect_column_values_to_not_be_null"
    },
    {
      "id": "c43d21ce-9926-49ed-a8f9-054c26abf09e",
      "kwargs": {
        "column": "oslcinstallment",
        "result_format": {
          "result_format": "COMPLETE",
          "return_unexpected_rows": true
        }
      },
      "meta": {
        "dimension": "correctness",
        "name": "oslcinstallment-ExpectColumnValuesToNotHaveDoubleSpace",
        "severity": "critical"
      },
      "severity": "critical",
      "type": "expect_column_values_to_not_have_double_space"
    },
    {
      "id": "9beb3d71-6bc2-4be7-b8ed-0d093755c572",
      "kwargs": {
        "column": "oslcinstallment",
        "result_format": {
          "result_format": "COMPLETE",
          "return_unexpected_rows": true
        }
      },
      "meta": {
        "dimension": "completeness",
        "name": "oslcinstallment-ExpectColumnValuesToNotBeNull",
        "severity": "critical"
      },
      "severity": "critical",
      "type": "expect_column_values_to_not_be_null"
    },
    {
      "id": "613e7e38-e1dc-4f07-9d7f-ff30ab36e59a",
      "kwargs": {
        "column": "osinsurance",
        "result_format": {
          "result_format": "COMPLETE",
          "return_unexpected_rows": true
        }
      },
      "meta": {
        "dimension": "correctness",
        "name": "osinsurance-ExpectColumnValuesToNotHaveDoubleSpace",
        "severity": "critical"
      },
      "severity": "critical",
      "type": "expect_column_values_to_not_have_double_space"
    },
    {
      "id": "53d4a90c-6dee-44af-b8d1-0196f43de6fc",
      "kwargs": {
        "column": "osinsurance",
        "result_format": {
          "result_format": "COMPLETE",
          "return_unexpected_rows": true
        }
      },
      "meta": {
        "dimension": "completeness",
        "name": "osinsurance-ExpectColumnValuesToNotBeNull",
        "severity": "critical"
      },
      "severity": "critical",
      "type": "expect_column_values_to_not_be_null"
    },
    {
      "id": "38ff3d31-00e8-49c3-96ac-822838847cd6",
      "kwargs": {
        "column": "oslcinsurance",
        "result_format": {
          "result_format": "COMPLETE",
          "return_unexpected_rows": true
        }
      },
      "meta": {
        "dimension": "correctness",
        "name": "oslcinsurance-ExpectColumnValuesToNotHaveDoubleSpace",
        "severity": "critical"
      },
      "severity": "critical",
      "type": "expect_column_values_to_not_have_double_space"
    },
    {
      "id": "6f60d3f1-0fde-4456-98e8-65c68b0b15fb",
      "kwargs": {
        "column": "oslcinsurance",
        "result_format": {
          "result_format": "COMPLETE",
          "return_unexpected_rows": true
        }
      },
      "meta": {
        "dimension": "completeness",
        "name": "oslcinsurance-ExpectColumnValuesToNotBeNull",
        "severity": "critical"
      },
      "severity": "critical",
      "type": "expect_column_values_to_not_be_null"
    },
    {
      "id": "f580044e-b319-4c12-b574-5df1659925a9",
      "kwargs": {
        "column": "arother",
        "result_format": {
          "result_format": "COMPLETE",
          "return_unexpected_rows": true
        }
      },
      "meta": {
        "dimension": "correctness",
        "name": "arother-ExpectColumnValuesToNotHaveDoubleSpace",
        "severity": "critical"
      },
      "severity": "critical",
      "type": "expect_column_values_to_not_have_double_space"
    },
    {
      "id": "1609d78b-b93f-4b50-a04a-e0a51d565db1",
      "kwargs": {
        "column": "arother",
        "result_format": {
          "result_format": "COMPLETE",
          "return_unexpected_rows": true
        }
      },
      "meta": {
        "dimension": "completeness",
        "name": "arother-ExpectColumnValuesToNotBeNull",
        "severity": "critical"
      },
      "severity": "critical",
      "type": "expect_column_values_to_not_be_null"
    },
    {
      "id": "f9870adb-d73d-433c-ad9b-8f3284d5748a",
      "kwargs": {
        "column": "fundingamount",
        "result_format": {
          "result_format": "COMPLETE",
          "return_unexpected_rows": true
        }
      },
      "meta": {
        "dimension": "correctness",
        "name": "fundingamount-ExpectColumnValuesToNotHaveDoubleSpace",
        "severity": "critical"
      },
      "severity": "critical",
      "type": "expect_column_values_to_not_have_double_space"
    },
    {
      "id": "5e74c980-d4a6-450a-91e1-f237addc1ada",
      "kwargs": {
        "column": "fundingamount",
        "result_format": {
          "result_format": "COMPLETE",
          "return_unexpected_rows": true
        }
      },
      "meta": {
        "dimension": "completeness",
        "name": "fundingamount-ExpectColumnValuesToNotBeNull",
        "severity": "critical"
      },
      "severity": "critical",
      "type": "expect_column_values_to_not_be_null"
    },
    {
      "id": "2731cea3-7bca-4064-af7a-282d0166e6e2",
      "kwargs": {
        "column": "outstandingprincipal",
        "result_format": {
          "result_format": "COMPLETE",
          "return_unexpected_rows": true
        }
      },
      "meta": {
        "dimension": "correctness",
        "name": "outstandingprincipal-ExpectColumnValuesToNotHaveDoubleSpace",
        "severity": "critical"
      },
      "severity": "critical",
      "type": "expect_column_values_to_not_have_double_space"
    },
    {
      "id": "22e4a383-163f-4e8a-95e7-48c825635033",
      "kwargs": {
        "column": "outstandingprincipal",
        "result_format": {
          "result_format": "COMPLETE",
          "return_unexpected_rows": true
        }
      },
      "meta": {
        "dimension": "completeness",
        "name": "outstandingprincipal-ExpectColumnValuesToNotBeNull",
        "severity": "critical"
      },
      "severity": "critical",
      "type": "expect_column_values_to_not_be_null"
    },
    {
      "id": "83a5a17f-d897-4e6b-879a-42d9e8493eef",
      "kwargs": {
        "column": "legalareaphone1",
        "result_format": {
          "result_format": "COMPLETE",
          "return_unexpected_rows": true
        }
      },
      "meta": {
        "dimension": "correctness",
        "name": "legalareaphone1-ExpectColumnValuesToNotHaveDoubleSpace",
        "severity": "critical"
      },
      "severity": "critical",
      "type": "expect_column_values_to_not_have_double_space"
    },
    {
      "id": "9d70cfdb-886e-4cb6-9cfe-d75605f4458b",
      "kwargs": {
        "column": "legalareaphone1",
        "result_format": {
          "result_format": "COMPLETE",
          "return_unexpected_rows": true
        }
      },
      "meta": {
        "dimension": "completeness",
        "name": "legalareaphone1-ExpectColumnValuesToNotBeNull",
        "severity": "critical"
      },
      "severity": "critical",
      "type": "expect_column_values_to_not_be_null"
    },
    {
      "id": "4617370a-a00c-4eb1-89b3-329111493618",
      "kwargs": {
        "column": "legalphone1",
        "result_format": {
          "result_format": "COMPLETE",
          "return_unexpected_rows": true
        }
      },
      "meta": {
        "dimension": "correctness",
        "name": "legalphone1-ExpectColumnValuesToNotHaveDoubleSpace",
        "severity": "critical"
      },
      "severity": "critical",
      "type": "expect_column_values_to_not_have_double_space"
    },
    {
      "id": "4e5fa8ac-fde0-4587-99de-973c6af8f6d4",
      "kwargs": {
        "column": "legalphone1",
        "result_format": {
          "result_format": "COMPLETE",
          "return_unexpected_rows": true
        }
      },
      "meta": {
        "dimension": "completeness",
        "name": "legalphone1-ExpectColumnValuesToNotBeNull",
        "severity": "critical"
      },
      "severity": "critical",
      "type": "expect_column_values_to_not_be_null"
    },
    {
      "id": "ae64018e-e79a-4108-9124-9770bdc7d6a7",
      "kwargs": {
        "column": "legalphone1",
        "result_format": {
          "result_format": "COMPLETE",
          "return_unexpected_rows": true
        }
      },
      "meta": {
        "dimension": "correctness",
        "name": "legalphone1-ExpectColumnValuesToMatchIndonesianPhoneRules",
        "severity": "warning"
      },
      "severity": "critical",
      "type": "expect_column_values_to_match_indonesian_phone_rules"
    },
    {
      "id": "517d85b9-866f-4ad2-8c5b-457d9d21e677",
      "kwargs": {
        "column": "companyareaphone1",
        "result_format": {
          "result_format": "COMPLETE",
          "return_unexpected_rows": true
        }
      },
      "meta": {
        "dimension": "correctness",
        "name": "companyareaphone1-ExpectColumnValuesToNotHaveDoubleSpace",
        "severity": "critical"
      },
      "severity": "critical",
      "type": "expect_column_values_to_not_have_double_space"
    },
    {
      "id": "5978c9e4-16f6-4ca9-99d2-096becf38cbe",
      "kwargs": {
        "column": "companyareaphone1",
        "result_format": {
          "result_format": "COMPLETE",
          "return_unexpected_rows": true
        }
      },
      "meta": {
        "dimension": "completeness",
        "name": "companyareaphone1-ExpectColumnValuesToNotBeNull",
        "severity": "critical"
      },
      "severity": "critical",
      "type": "expect_column_values_to_not_be_null"
    },
    {
      "id": "7f2084c3-b169-4609-bb40-dae5f2d69df2",
      "kwargs": {
        "column": "companyphone1",
        "result_format": {
          "result_format": "COMPLETE",
          "return_unexpected_rows": true
        }
      },
      "meta": {
        "dimension": "correctness",
        "name": "companyphone1-ExpectColumnValuesToNotHaveDoubleSpace",
        "severity": "critical"
      },
      "severity": "critical",
      "type": "expect_column_values_to_not_have_double_space"
    },
    {
      "id": "a2056694-93a8-4570-95c2-c5ae83fb0e1e",
      "kwargs": {
        "column": "companyphone1",
        "result_format": {
          "result_format": "COMPLETE",
          "return_unexpected_rows": true
        }
      },
      "meta": {
        "dimension": "completeness",
        "name": "companyphone1-ExpectColumnValuesToNotBeNull",
        "severity": "critical"
      },
      "severity": "critical",
      "type": "expect_column_values_to_not_be_null"
    },
    {
      "id": "b3a6e620-e023-4696-a955-f30738a32e8f",
      "kwargs": {
        "column": "companyphone1",
        "result_format": {
          "result_format": "COMPLETE",
          "return_unexpected_rows": true
        }
      },
      "meta": {
        "dimension": "correctness",
        "name": "companyphone1-ExpectColumnValuesToMatchIndonesianPhoneRules",
        "severity": "warning"
      },
      "severity": "critical",
      "type": "expect_column_values_to_match_indonesian_phone_rules"
    },
    {
      "id": "600bb03a-a0a0-4afa-84aa-75f23a44d557",
      "kwargs": {
        "column": "residenceareaphone1",
        "result_format": {
          "result_format": "COMPLETE",
          "return_unexpected_rows": true
        }
      },
      "meta": {
        "dimension": "correctness",
        "name": "residenceareaphone1-ExpectColumnValuesToNotHaveDoubleSpace",
        "severity": "critical"
      },
      "severity": "critical",
      "type": "expect_column_values_to_not_have_double_space"
    },
    {
      "id": "40b50edc-0f8e-4182-9bd3-15fe9f636a28",
      "kwargs": {
        "column": "residenceareaphone1",
        "result_format": {
          "result_format": "COMPLETE",
          "return_unexpected_rows": true
        }
      },
      "meta": {
        "dimension": "completeness",
        "name": "residenceareaphone1-ExpectColumnValuesToNotBeNull",
        "severity": "critical"
      },
      "severity": "critical",
      "type": "expect_column_values_to_not_be_null"
    },
    {
      "id": "e31359bd-4bfc-423b-8bb7-fa889430214c",
      "kwargs": {
        "column": "residencephone1",
        "result_format": {
          "result_format": "COMPLETE",
          "return_unexpected_rows": true
        }
      },
      "meta": {
        "dimension": "correctness",
        "name": "residencephone1-ExpectColumnValuesToNotHaveDoubleSpace",
        "severity": "critical"
      },
      "severity": "critical",
      "type": "expect_column_values_to_not_have_double_space"
    },
    {
      "id": "c01bd979-77a8-4053-87aa-e60c51d9f6ab",
      "kwargs": {
        "column": "residencephone1",
        "result_format": {
          "result_format": "COMPLETE",
          "return_unexpected_rows": true
        }
      },
      "meta": {
        "dimension": "completeness",
        "name": "residencephone1-ExpectColumnValuesToNotBeNull",
        "severity": "critical"
      },
      "severity": "critical",
      "type": "expect_column_values_to_not_be_null"
    },
    {
      "id": "33364097-9cb5-4a03-a34d-6da9b6c8d3a1",
      "kwargs": {
        "column": "residencephone1",
        "result_format": {
          "result_format": "COMPLETE",
          "return_unexpected_rows": true
        }
      },
      "meta": {
        "dimension": "correctness",
        "name": "residencephone1-ExpectColumnValuesToMatchIndonesianPhoneRules",
        "severity": "warning"
      },
      "severity": "critical",
      "type": "expect_column_values_to_match_indonesian_phone_rules"
    },
    {
      "id": "c13cb754-8139-43eb-803c-9dfb844e26df",
      "kwargs": {
        "column": "mobilephone",
        "result_format": {
          "result_format": "COMPLETE",
          "return_unexpected_rows": true
        }
      },
      "meta": {
        "dimension": "correctness",
        "name": "mobilephone-ExpectColumnValuesToNotHaveDoubleSpace",
        "severity": "critical"
      },
      "severity": "critical",
      "type": "expect_column_values_to_not_have_double_space"
    },
    {
      "id": "d1600580-13f1-43ce-901c-35f82daa0fd7",
      "kwargs": {
        "column": "mobilephone",
        "result_format": {
          "result_format": "COMPLETE",
          "return_unexpected_rows": true
        }
      },
      "meta": {
        "dimension": "completeness",
        "name": "mobilephone-ExpectColumnValuesToNotBeNull",
        "severity": "critical"
      },
      "severity": "critical",
      "type": "expect_column_values_to_not_be_null"
    },
    {
      "id": "ca8e07c7-64be-4e25-8289-7183e3ad8997",
      "kwargs": {
        "column": "mobilephone",
        "result_format": {
          "result_format": "COMPLETE",
          "return_unexpected_rows": true
        }
      },
      "meta": {
        "dimension": "correctness",
        "name": "mobilephone-ExpectColumnValuesToMatchIndonesianPhoneRules",
        "severity": "warning"
      },
      "severity": "critical",
      "type": "expect_column_values_to_match_indonesian_phone_rules"
    },
    {
      "id": "5b1cfd51-62b7-457d-9fd8-540412b28b21",
      "kwargs": {
        "column": "companyareafax",
        "result_format": {
          "result_format": "COMPLETE",
          "return_unexpected_rows": true
        }
      },
      "meta": {
        "dimension": "correctness",
        "name": "companyareafax-ExpectColumnValuesToNotHaveDoubleSpace",
        "severity": "critical"
      },
      "severity": "critical",
      "type": "expect_column_values_to_not_have_double_space"
    },
    {
      "id": "4d3dbed2-2eb9-4360-9534-3e8cabc038da",
      "kwargs": {
        "column": "companyareafax",
        "result_format": {
          "result_format": "COMPLETE",
          "return_unexpected_rows": true
        }
      },
      "meta": {
        "dimension": "completeness",
        "name": "companyareafax-ExpectColumnValuesToNotBeNull",
        "severity": "critical"
      },
      "severity": "critical",
      "type": "expect_column_values_to_not_be_null"
    },
    {
      "id": "198a9ef7-fdb5-4d63-90d0-07135a471b20",
      "kwargs": {
        "column": "companyfax",
        "result_format": {
          "result_format": "COMPLETE",
          "return_unexpected_rows": true
        }
      },
      "meta": {
        "dimension": "correctness",
        "name": "companyfax-ExpectColumnValuesToNotHaveDoubleSpace",
        "severity": "critical"
      },
      "severity": "critical",
      "type": "expect_column_values_to_not_have_double_space"
    },
    {
      "id": "eed3f1d8-d1c0-4410-a20f-f9bfc2d41313",
      "kwargs": {
        "column": "companyfax",
        "result_format": {
          "result_format": "COMPLETE",
          "return_unexpected_rows": true
        }
      },
      "meta": {
        "dimension": "completeness",
        "name": "companyfax-ExpectColumnValuesToNotBeNull",
        "severity": "critical"
      },
      "severity": "critical",
      "type": "expect_column_values_to_not_be_null"
    },
    {
      "id": "666c2842-5a2d-4cc1-8dcf-eb5071e935ce",
      "kwargs": {
        "column": "companyfax",
        "regex": "^[0-9]{14}$",
        "result_format": {
          "result_format": "COMPLETE",
          "return_unexpected_rows": true
        }
      },
      "meta": {
        "dimension": "correctness",
        "name": "companyfax-ExpectColumnValuesToMatchRegex",
        "severity": "critical"
      },
      "severity": "critical",
      "type": "expect_column_values_to_match_regex"
    },
    {
      "id": "229bd00b-8502-415c-8121-fdef4383f351",
      "kwargs": {
        "column": "legalareafax",
        "result_format": {
          "result_format": "COMPLETE",
          "return_unexpected_rows": true
        }
      },
      "meta": {
        "dimension": "correctness",
        "name": "legalareafax-ExpectColumnValuesToNotHaveDoubleSpace",
        "severity": "critical"
      },
      "severity": "critical",
      "type": "expect_column_values_to_not_have_double_space"
    },
    {
      "id": "3a585088-48d7-4f1f-b96e-5f96f2af2010",
      "kwargs": {
        "column": "legalareafax",
        "result_format": {
          "result_format": "COMPLETE",
          "return_unexpected_rows": true
        }
      },
      "meta": {
        "dimension": "completeness",
        "name": "legalareafax-ExpectColumnValuesToNotBeNull",
        "severity": "critical"
      },
      "severity": "critical",
      "type": "expect_column_values_to_not_be_null"
    },
    {
      "id": "d20b6900-f882-48da-9c66-e44c7a3ff0a1",
      "kwargs": {
        "column": "legalfax",
        "result_format": {
          "result_format": "COMPLETE",
          "return_unexpected_rows": true
        }
      },
      "meta": {
        "dimension": "correctness",
        "name": "legalfax-ExpectColumnValuesToNotHaveDoubleSpace",
        "severity": "critical"
      },
      "severity": "critical",
      "type": "expect_column_values_to_not_have_double_space"
    },
    {
      "id": "ac9b4bbb-6d38-4aff-a61f-74702be77531",
      "kwargs": {
        "column": "legalfax",
        "result_format": {
          "result_format": "COMPLETE",
          "return_unexpected_rows": true
        }
      },
      "meta": {
        "dimension": "completeness",
        "name": "legalfax-ExpectColumnValuesToNotBeNull",
        "severity": "critical"
      },
      "severity": "critical",
      "type": "expect_column_values_to_not_be_null"
    },
    {
      "id": "ac39a29f-faa7-4e63-bb83-cf53e7f776d1",
      "kwargs": {
        "column": "legalfax",
        "regex": "^[0-9]{14}$",
        "result_format": {
          "result_format": "COMPLETE",
          "return_unexpected_rows": true
        }
      },
      "meta": {
        "dimension": "correctness",
        "name": "legalfax-ExpectColumnValuesToMatchRegex",
        "severity": "critical"
      },
      "severity": "critical",
      "type": "expect_column_values_to_match_regex"
    },
    {
      "id": "318bb370-959b-4a98-a2d2-d8f7e6f265df",
      "kwargs": {
        "column": "residenceareafax",
        "result_format": {
          "result_format": "COMPLETE",
          "return_unexpected_rows": true
        }
      },
      "meta": {
        "dimension": "correctness",
        "name": "residenceareafax-ExpectColumnValuesToNotHaveDoubleSpace",
        "severity": "critical"
      },
      "severity": "critical",
      "type": "expect_column_values_to_not_have_double_space"
    },
    {
      "id": "76525ef0-3d4e-4c92-a70f-e4f0bb8b321a",
      "kwargs": {
        "column": "residenceareafax",
        "result_format": {
          "result_format": "COMPLETE",
          "return_unexpected_rows": true
        }
      },
      "meta": {
        "dimension": "completeness",
        "name": "residenceareafax-ExpectColumnValuesToNotBeNull",
        "severity": "critical"
      },
      "severity": "critical",
      "type": "expect_column_values_to_not_be_null"
    },
    {
      "id": "16a64750-79b4-4b27-b186-d2a09f99871b",
      "kwargs": {
        "column": "residencefax",
        "result_format": {
          "result_format": "COMPLETE",
          "return_unexpected_rows": true
        }
      },
      "meta": {
        "dimension": "correctness",
        "name": "residencefax-ExpectColumnValuesToNotHaveDoubleSpace",
        "severity": "critical"
      },
      "severity": "critical",
      "type": "expect_column_values_to_not_have_double_space"
    },
    {
      "id": "23a9f24d-0e3c-4cdd-8e6e-23fa4d11eb24",
      "kwargs": {
        "column": "residencefax",
        "result_format": {
          "result_format": "COMPLETE",
          "return_unexpected_rows": true
        }
      },
      "meta": {
        "dimension": "completeness",
        "name": "residencefax-ExpectColumnValuesToNotBeNull",
        "severity": "critical"
      },
      "severity": "critical",
      "type": "expect_column_values_to_not_be_null"
    },
    {
      "id": "d0d6f21a-623d-4c6d-9c02-51127df5ae84",
      "kwargs": {
        "column": "residencefax",
        "regex": "^[0-9]{14}$",
        "result_format": {
          "result_format": "COMPLETE",
          "return_unexpected_rows": true
        }
      },
      "meta": {
        "dimension": "correctness",
        "name": "residencefax-ExpectColumnValuesToMatchRegex",
        "severity": "critical"
      },
      "severity": "critical",
      "type": "expect_column_values_to_match_regex"
    },
    {
      "id": "bad7386d-64d8-4277-99e8-077a26aea298",
      "kwargs": {
        "column": "taskdate",
        "result_format": {
          "result_format": "COMPLETE",
          "return_unexpected_rows": true
        }
      },
      "meta": {
        "dimension": "correctness",
        "name": "taskdate-ExpectColumnValuesToNotHaveDoubleSpace",
        "severity": "critical"
      },
      "severity": "critical",
      "type": "expect_column_values_to_not_have_double_space"
    },
    {
      "id": "6f30e7b6-ee5c-435e-a436-8313bd4f58e1",
      "kwargs": {
        "column": "taskdate",
        "result_format": {
          "result_format": "COMPLETE",
          "return_unexpected_rows": true
        }
      },
      "meta": {
        "dimension": "completeness",
        "name": "taskdate-ExpectColumnValuesToNotBeNull",
        "severity": "critical"
      },
      "severity": "critical",
      "type": "expect_column_values_to_not_be_null"
    },
    {
      "id": "84c833f9-64b1-4b0e-b5fe-aee96c932088",
      "kwargs": {
        "column": "pastduedays",
        "min_value": 0.0,
        "result_format": {
          "result_format": "COMPLETE",
          "return_unexpected_rows": true
        }
      },
      "meta": {
        "dimension": "correctness",
        "name": "pastduedays-ExpectColumnValuesToBeBetween",
        "severity": "warning"
      },
      "severity": "critical",
      "type": "expect_column_values_to_be_between"
    },
    {
      "id": "a392cbc5-bc69-4269-a094-faf98ddf4b75",
      "kwargs": {
        "column": "pastduedays",
        "result_format": {
          "result_format": "COMPLETE",
          "return_unexpected_rows": true
        }
      },
      "meta": {
        "dimension": "completeness",
        "name": "pastduedays-ExpectColumnValuesToNotBeNull",
        "severity": "critical"
      },
      "severity": "critical",
      "type": "expect_column_values_to_not_be_null"
    },
    {
      "id": "263ff405-9974-4289-97a4-601736327689",
      "kwargs": {
        "column": "producttype",
        "result_format": {
          "result_format": "COMPLETE",
          "return_unexpected_rows": true
        }
      },
      "meta": {
        "dimension": "correctness",
        "name": "producttype-ExpectColumnValuesToNotHaveDoubleSpace",
        "severity": "critical"
      },
      "severity": "critical",
      "type": "expect_column_values_to_not_have_double_space"
    },
    {
      "id": "bf37b4a3-cbaa-4632-8b30-0a81ff62f24e",
      "kwargs": {
        "column": "producttype",
        "result_format": {
          "result_format": "COMPLETE",
          "return_unexpected_rows": true
        }
      },
      "meta": {
        "dimension": "completeness",
        "name": "producttype-ExpectColumnValuesToNotBeNull",
        "severity": "critical"
      },
      "severity": "critical",
      "type": "expect_column_values_to_not_be_null"
    },
    {
      "id": "0ec06a61-e51e-4a6d-ad8e-216de8475967",
      "kwargs": {
        "column": "emergencyareaphone1",
        "result_format": {
          "result_format": "COMPLETE",
          "return_unexpected_rows": true
        }
      },
      "meta": {
        "dimension": "correctness",
        "name": "emergencyareaphone1-ExpectColumnValuesToNotHaveDoubleSpace",
        "severity": "critical"
      },
      "severity": "critical",
      "type": "expect_column_values_to_not_have_double_space"
    },
    {
      "id": "84e02fb8-48e6-4fae-9060-d09dd02ea646",
      "kwargs": {
        "column": "emergencyareaphone1",
        "result_format": {
          "result_format": "COMPLETE",
          "return_unexpected_rows": true
        }
      },
      "meta": {
        "dimension": "completeness",
        "name": "emergencyareaphone1-ExpectColumnValuesToNotBeNull",
        "severity": "critical"
      },
      "severity": "critical",
      "type": "expect_column_values_to_not_be_null"
    },
    {
      "id": "678f3ba0-cdef-45bb-8a51-8223be366c7b",
      "kwargs": {
        "column": "emergencyphone1",
        "result_format": {
          "result_format": "COMPLETE",
          "return_unexpected_rows": true
        }
      },
      "meta": {
        "dimension": "correctness",
        "name": "emergencyphone1-ExpectColumnValuesToNotHaveDoubleSpace",
        "severity": "critical"
      },
      "severity": "critical",
      "type": "expect_column_values_to_not_have_double_space"
    },
    {
      "id": "8f2151af-1a68-406b-b9ef-2795636bd431",
      "kwargs": {
        "column": "emergencyphone1",
        "result_format": {
          "result_format": "COMPLETE",
          "return_unexpected_rows": true
        }
      },
      "meta": {
        "dimension": "completeness",
        "name": "emergencyphone1-ExpectColumnValuesToNotBeNull",
        "severity": "critical"
      },
      "severity": "critical",
      "type": "expect_column_values_to_not_be_null"
    },
    {
      "id": "031b016b-7c9e-45da-b1e1-675c26de8c80",
      "kwargs": {
        "column": "emergencyphone1",
        "result_format": {
          "result_format": "COMPLETE",
          "return_unexpected_rows": true
        }
      },
      "meta": {
        "dimension": "correctness",
        "name": "emergencyphone1-ExpectColumnValuesToMatchIndonesianPhoneRules",
        "severity": "warning"
      },
      "severity": "critical",
      "type": "expect_column_values_to_match_indonesian_phone_rules"
    },
    {
      "id": "b453f39c-c5f4-4521-9bc4-8a855ef0fa5b",
      "kwargs": {
        "column": "emergencyareaphone2",
        "result_format": {
          "result_format": "COMPLETE",
          "return_unexpected_rows": true
        }
      },
      "meta": {
        "dimension": "correctness",
        "name": "emergencyareaphone2-ExpectColumnValuesToNotHaveDoubleSpace",
        "severity": "critical"
      },
      "severity": "critical",
      "type": "expect_column_values_to_not_have_double_space"
    },
    {
      "id": "6f1438e7-488d-4937-97e9-dc5f270ae63c",
      "kwargs": {
        "column": "emergencyareaphone2",
        "result_format": {
          "result_format": "COMPLETE",
          "return_unexpected_rows": true
        }
      },
      "meta": {
        "dimension": "completeness",
        "name": "emergencyareaphone2-ExpectColumnValuesToNotBeNull",
        "severity": "critical"
      },
      "severity": "critical",
      "type": "expect_column_values_to_not_be_null"
    },
    {
      "id": "2f3bb00f-6c79-4313-bcd9-0721272a2e73",
      "kwargs": {
        "column": "emergencyphone2",
        "result_format": {
          "result_format": "COMPLETE",
          "return_unexpected_rows": true
        }
      },
      "meta": {
        "dimension": "correctness",
        "name": "emergencyphone2-ExpectColumnValuesToNotHaveDoubleSpace",
        "severity": "critical"
      },
      "severity": "critical",
      "type": "expect_column_values_to_not_have_double_space"
    },
    {
      "id": "92f27952-9665-4e7f-9a48-1cfc9e4dff6b",
      "kwargs": {
        "column": "emergencyphone2",
        "result_format": {
          "result_format": "COMPLETE",
          "return_unexpected_rows": true
        }
      },
      "meta": {
        "dimension": "completeness",
        "name": "emergencyphone2-ExpectColumnValuesToNotBeNull",
        "severity": "critical"
      },
      "severity": "critical",
      "type": "expect_column_values_to_not_be_null"
    },
    {
      "id": "e841dbea-8322-417f-b290-be448a514197",
      "kwargs": {
        "column": "emergencyphone2",
        "result_format": {
          "result_format": "COMPLETE",
          "return_unexpected_rows": true
        }
      },
      "meta": {
        "dimension": "correctness",
        "name": "emergencyphone2-ExpectColumnValuesToMatchIndonesianPhoneRules",
        "severity": "warning"
      },
      "severity": "critical",
      "type": "expect_column_values_to_match_indonesian_phone_rules"
    },
    {
      "id": "1690a083-5fdf-4fcb-8e7e-cf2365900379",
      "kwargs": {
        "column": "emergencycontactname",
        "result_format": {
          "result_format": "COMPLETE",
          "return_unexpected_rows": true
        }
      },
      "meta": {
        "dimension": "correctness",
        "name": "emergencycontactname-ExpectColumnValuesToNotHaveDoubleSpace",
        "severity": "critical"
      },
      "severity": "critical",
      "type": "expect_column_values_to_not_have_double_space"
    },
    {
      "id": "788c6440-2d43-4424-968c-d4464a7d2e12",
      "kwargs": {
        "column": "emergencycontactname",
        "result_format": {
          "result_format": "COMPLETE",
          "return_unexpected_rows": true
        }
      },
      "meta": {
        "dimension": "completeness",
        "name": "emergencycontactname-ExpectColumnValuesToNotBeNull",
        "severity": "critical"
      },
      "severity": "critical",
      "type": "expect_column_values_to_not_be_null"
    },
    {
      "id": "7ffb6242-033b-40e7-a969-3a1ef80b6681",
      "kwargs": {
        "column": "emergencycontactname",
        "result_format": {
          "result_format": "COMPLETE",
          "return_unexpected_rows": true
        }
      },
      "meta": {
        "dimension": "correctness",
        "name": "emergencycontactname-ExpectColumnValuesToNotContainSpecialCharacters",
        "severity": "critical"
      },
      "severity": "critical",
      "type": "expect_column_values_to_not_contain_special_characters"
    },
    {
      "id": "10bfead7-8a5a-44d7-af4a-9ac50dc9f1ac",
      "kwargs": {
        "column": "residenceareaphone2",
        "result_format": {
          "result_format": "COMPLETE",
          "return_unexpected_rows": true
        }
      },
      "meta": {
        "dimension": "correctness",
        "name": "residenceareaphone2-ExpectColumnValuesToNotHaveDoubleSpace",
        "severity": "critical"
      },
      "severity": "critical",
      "type": "expect_column_values_to_not_have_double_space"
    },
    {
      "id": "a0bddfc3-0504-4e9f-83c4-4746027b17a5",
      "kwargs": {
        "column": "residenceareaphone2",
        "result_format": {
          "result_format": "COMPLETE",
          "return_unexpected_rows": true
        }
      },
      "meta": {
        "dimension": "completeness",
        "name": "residenceareaphone2-ExpectColumnValuesToNotBeNull",
        "severity": "critical"
      },
      "severity": "critical",
      "type": "expect_column_values_to_not_be_null"
    },
    {
      "id": "4e13e592-344e-4837-bfd6-223f0f0b8b98",
      "kwargs": {
        "column": "residencephone2",
        "result_format": {
          "result_format": "COMPLETE",
          "return_unexpected_rows": true
        }
      },
      "meta": {
        "dimension": "correctness",
        "name": "residencephone2-ExpectColumnValuesToNotHaveDoubleSpace",
        "severity": "critical"
      },
      "severity": "critical",
      "type": "expect_column_values_to_not_have_double_space"
    },
    {
      "id": "b681b1c5-e0c8-4e92-84e0-97899938371a",
      "kwargs": {
        "column": "residencephone2",
        "result_format": {
          "result_format": "COMPLETE",
          "return_unexpected_rows": true
        }
      },
      "meta": {
        "dimension": "completeness",
        "name": "residencephone2-ExpectColumnValuesToNotBeNull",
        "severity": "critical"
      },
      "severity": "critical",
      "type": "expect_column_values_to_not_be_null"
    },
    {
      "id": "90672257-32c1-4723-af54-65929f0a3cb6",
      "kwargs": {
        "column": "residencephone2",
        "result_format": {
          "result_format": "COMPLETE",
          "return_unexpected_rows": true
        }
      },
      "meta": {
        "dimension": "correctness",
        "name": "residencephone2-ExpectColumnValuesToMatchIndonesianPhoneRules",
        "severity": "warning"
      },
      "severity": "critical",
      "type": "expect_column_values_to_match_indonesian_phone_rules"
    },
    {
      "id": "230471df-88aa-466e-b677-42283485be94",
      "kwargs": {
        "column": "legalareaphone2",
        "result_format": {
          "result_format": "COMPLETE",
          "return_unexpected_rows": true
        }
      },
      "meta": {
        "dimension": "correctness",
        "name": "legalareaphone2-ExpectColumnValuesToNotHaveDoubleSpace",
        "severity": "critical"
      },
      "severity": "critical",
      "type": "expect_column_values_to_not_have_double_space"
    },
    {
      "id": "d7b4b9bf-f6b8-4cc7-a6ee-98328124230a",
      "kwargs": {
        "column": "legalareaphone2",
        "result_format": {
          "result_format": "COMPLETE",
          "return_unexpected_rows": true
        }
      },
      "meta": {
        "dimension": "completeness",
        "name": "legalareaphone2-ExpectColumnValuesToNotBeNull",
        "severity": "critical"
      },
      "severity": "critical",
      "type": "expect_column_values_to_not_be_null"
    },
    {
      "id": "f0ac0e18-8206-46b1-8c3f-460c8a2fdc2e",
      "kwargs": {
        "column": "legalphone2",
        "result_format": {
          "result_format": "COMPLETE",
          "return_unexpected_rows": true
        }
      },
      "meta": {
        "dimension": "correctness",
        "name": "legalphone2-ExpectColumnValuesToNotHaveDoubleSpace",
        "severity": "critical"
      },
      "severity": "critical",
      "type": "expect_column_values_to_not_have_double_space"
    },
    {
      "id": "3de78d5d-1587-46f7-83b3-4d7586d51357",
      "kwargs": {
        "column": "legalphone2",
        "result_format": {
          "result_format": "COMPLETE",
          "return_unexpected_rows": true
        }
      },
      "meta": {
        "dimension": "completeness",
        "name": "legalphone2-ExpectColumnValuesToNotBeNull",
        "severity": "critical"
      },
      "severity": "critical",
      "type": "expect_column_values_to_not_be_null"
    },
    {
      "id": "61503e0d-7664-4190-8abe-c28d81db6fd6",
      "kwargs": {
        "column": "legalphone2",
        "result_format": {
          "result_format": "COMPLETE",
          "return_unexpected_rows": true
        }
      },
      "meta": {
        "dimension": "correctness",
        "name": "legalphone2-ExpectColumnValuesToMatchIndonesianPhoneRules",
        "severity": "warning"
      },
      "severity": "critical",
      "type": "expect_column_values_to_match_indonesian_phone_rules"
    },
    {
      "id": "12124081-5b8b-40c2-9347-6694a179a9f5",
      "kwargs": {
        "column": "areaid",
        "result_format": {
          "result_format": "COMPLETE",
          "return_unexpected_rows": true
        }
      },
      "meta": {
        "dimension": "correctness",
        "name": "areaid-ExpectColumnValuesToNotHaveDoubleSpace",
        "severity": "critical"
      },
      "severity": "critical",
      "type": "expect_column_values_to_not_have_double_space"
    },
    {
      "id": "0d53bf99-467e-4d4b-8814-5c201ed10bcc",
      "kwargs": {
        "column": "areaid",
        "result_format": {
          "result_format": "COMPLETE",
          "return_unexpected_rows": true
        }
      },
      "meta": {
        "dimension": "completeness",
        "name": "areaid-ExpectColumnValuesToNotBeNull",
        "severity": "critical"
      },
      "severity": "critical",
      "type": "expect_column_values_to_not_be_null"
    },
    {
      "id": "09988490-cde6-4261-86be-290bddaae3f7",
      "kwargs": {
        "column": "installmentstepdown",
        "min_value": 0.0,
        "result_format": {
          "result_format": "COMPLETE",
          "return_unexpected_rows": true
        }
      },
      "meta": {
        "dimension": "correctness",
        "name": "installmentstepdown-ExpectColumnValuesToBeBetween",
        "severity": "warning"
      },
      "severity": "critical",
      "type": "expect_column_values_to_be_between"
    },
    {
      "id": "c7e14871-48d3-4046-80d5-23a9f8df6c9b",
      "kwargs": {
        "column": "installmentstepdown",
        "result_format": {
          "result_format": "COMPLETE",
          "return_unexpected_rows": true
        }
      },
      "meta": {
        "dimension": "completeness",
        "name": "installmentstepdown-ExpectColumnValuesToNotBeNull",
        "severity": "critical"
      },
      "severity": "critical",
      "type": "expect_column_values_to_not_be_null"
    },
    {
      "id": "d8f29f2a-acbe-442f-8096-de25c3ec35ac",
      "kwargs": {
        "column": "realtenor",
        "min_value": 0.0,
        "result_format": {
          "result_format": "COMPLETE",
          "return_unexpected_rows": true
        }
      },
      "meta": {
        "dimension": "correctness",
        "name": "realtenor-ExpectColumnValuesToBeBetween",
        "severity": "warning"
      },
      "severity": "critical",
      "type": "expect_column_values_to_be_between"
    },
    {
      "id": "8da75679-4529-4698-b07d-9a51677fcd0f",
      "kwargs": {
        "column": "realtenor",
        "result_format": {
          "result_format": "COMPLETE",
          "return_unexpected_rows": true
        }
      },
      "meta": {
        "dimension": "completeness",
        "name": "realtenor-ExpectColumnValuesToNotBeNull",
        "severity": "critical"
      },
      "severity": "critical",
      "type": "expect_column_values_to_not_be_null"
    },
    {
      "id": "1cf103db-c9b1-4cbe-9bfc-d778ee9f4f24",
      "kwargs": {
        "column": "lastpaiddate",
        "result_format": {
          "result_format": "COMPLETE",
          "return_unexpected_rows": true
        }
      },
      "meta": {
        "dimension": "correctness",
        "name": "lastpaiddate-ExpectColumnValuesToNotHaveDoubleSpace",
        "severity": "critical"
      },
      "severity": "critical",
      "type": "expect_column_values_to_not_have_double_space"
    },
    {
      "id": "a53e0ab5-7d8b-48c0-af08-34eaa07824c5",
      "kwargs": {
        "column": "lastpaiddate",
        "result_format": {
          "result_format": "COMPLETE",
          "return_unexpected_rows": true
        }
      },
      "meta": {
        "dimension": "completeness",
        "name": "lastpaiddate-ExpectColumnValuesToNotBeNull",
        "severity": "critical"
      },
      "severity": "critical",
      "type": "expect_column_values_to_not_be_null"
    },
    {
      "id": "56960fa9-f2d7-49e5-8aa5-96a95fbf6945",
      "kwargs": {
        "column": "lastduedate",
        "result_format": {
          "result_format": "COMPLETE",
          "return_unexpected_rows": true
        }
      },
      "meta": {
        "dimension": "correctness",
        "name": "lastduedate-ExpectColumnValuesToNotHaveDoubleSpace",
        "severity": "critical"
      },
      "severity": "critical",
      "type": "expect_column_values_to_not_have_double_space"
    },
    {
      "id": "0a263e2f-5b15-41b9-8e44-5ea743fff38a",
      "kwargs": {
        "column": "lastduedate",
        "result_format": {
          "result_format": "COMPLETE",
          "return_unexpected_rows": true
        }
      },
      "meta": {
        "dimension": "completeness",
        "name": "lastduedate-ExpectColumnValuesToNotBeNull",
        "severity": "critical"
      },
      "severity": "critical",
      "type": "expect_column_values_to_not_be_null"
    },
    {
      "id": "f4edf7dd-c316-4d97-bf3e-0028c299976f",
      "kwargs": {
        "column": "paymenttypedesc",
        "result_format": {
          "result_format": "COMPLETE",
          "return_unexpected_rows": true
        }
      },
      "meta": {
        "dimension": "correctness",
        "name": "paymenttypedesc-ExpectColumnValuesToNotHaveDoubleSpace",
        "severity": "critical"
      },
      "severity": "critical",
      "type": "expect_column_values_to_not_have_double_space"
    },
    {
      "id": "322e54ed-94e8-42fb-a0be-629d657c803d",
      "kwargs": {
        "column": "paymenttypedesc",
        "result_format": {
          "result_format": "COMPLETE",
          "return_unexpected_rows": true
        }
      },
      "meta": {
        "dimension": "completeness",
        "name": "paymenttypedesc-ExpectColumnValuesToNotBeNull",
        "severity": "critical"
      },
      "severity": "critical",
      "type": "expect_column_values_to_not_be_null"
    },
    {
      "id": "89897fb4-8624-4c39-97df-4bbbfabc1b87",
      "kwargs": {
        "column": "bankaccountname",
        "result_format": {
          "result_format": "COMPLETE",
          "return_unexpected_rows": true
        }
      },
      "meta": {
        "dimension": "correctness",
        "name": "bankaccountname-ExpectColumnValuesToNotHaveDoubleSpace",
        "severity": "critical"
      },
      "severity": "critical",
      "type": "expect_column_values_to_not_have_double_space"
    },
    {
      "id": "d0611a83-6e8a-4aa2-a98f-c462d8956b99",
      "kwargs": {
        "column": "bankaccountname",
        "result_format": {
          "result_format": "COMPLETE",
          "return_unexpected_rows": true
        }
      },
      "meta": {
        "dimension": "completeness",
        "name": "bankaccountname-ExpectColumnValuesToNotBeNull",
        "severity": "critical"
      },
      "severity": "critical",
      "type": "expect_column_values_to_not_be_null"
    },
    {
      "id": "a26a6b1c-f843-44ea-9c9d-2dedb321d56e",
      "kwargs": {
        "column": "bankaccountname",
        "result_format": {
          "result_format": "COMPLETE",
          "return_unexpected_rows": true
        }
      },
      "meta": {
        "dimension": "correctness",
        "name": "bankaccountname-ExpectColumnValuesToNotContainSpecialCharacters",
        "severity": "critical"
      },
      "severity": "critical",
      "type": "expect_column_values_to_not_contain_special_characters"
    },
    {
      "id": "da1e3d65-6ce7-4afd-991d-cab41a6a59da",
      "kwargs": {
        "column": "spousemobilephone",
        "result_format": {
          "result_format": "COMPLETE",
          "return_unexpected_rows": true
        }
      },
      "meta": {
        "dimension": "correctness",
        "name": "spousemobilephone-ExpectColumnValuesToNotHaveDoubleSpace",
        "severity": "critical"
      },
      "severity": "critical",
      "type": "expect_column_values_to_not_have_double_space"
    },
    {
      "id": "60e4c632-31ad-448c-a0a3-c879acf1c015",
      "kwargs": {
        "column": "spousemobilephone",
        "result_format": {
          "result_format": "COMPLETE",
          "return_unexpected_rows": true
        }
      },
      "meta": {
        "dimension": "completeness",
        "name": "spousemobilephone-ExpectColumnValuesToNotBeNull",
        "severity": "critical"
      },
      "severity": "critical",
      "type": "expect_column_values_to_not_be_null"
    },
    {
      "id": "19959dd1-bcd6-42eb-bd97-46327c391590",
      "kwargs": {
        "column": "spousemobilephone",
        "result_format": {
          "result_format": "COMPLETE",
          "return_unexpected_rows": true
        }
      },
      "meta": {
        "dimension": "correctness",
        "name": "spousemobilephone-ExpectColumnValuesToMatchIndonesianPhoneRules",
        "severity": "warning"
      },
      "severity": "critical",
      "type": "expect_column_values_to_match_indonesian_phone_rules"
    },
    {
      "id": "b3fff10c-7eb4-4e05-82b1-eb969c38daaf",
      "kwargs": {
        "column": "companyareaphone2",
        "result_format": {
          "result_format": "COMPLETE",
          "return_unexpected_rows": true
        }
      },
      "meta": {
        "dimension": "correctness",
        "name": "companyareaphone2-ExpectColumnValuesToNotHaveDoubleSpace",
        "severity": "critical"
      },
      "severity": "critical",
      "type": "expect_column_values_to_not_have_double_space"
    },
    {
      "id": "ea3c132c-95e1-4f5f-8552-6bb4103dc4db",
      "kwargs": {
        "column": "companyareaphone2",
        "result_format": {
          "result_format": "COMPLETE",
          "return_unexpected_rows": true
        }
      },
      "meta": {
        "dimension": "completeness",
        "name": "companyareaphone2-ExpectColumnValuesToNotBeNull",
        "severity": "critical"
      },
      "severity": "critical",
      "type": "expect_column_values_to_not_be_null"
    },
    {
      "id": "2bdfa3f0-d26d-414b-b224-321223a1249b",
      "kwargs": {
        "column": "companyphone2",
        "result_format": {
          "result_format": "COMPLETE",
          "return_unexpected_rows": true
        }
      },
      "meta": {
        "dimension": "correctness",
        "name": "companyphone2-ExpectColumnValuesToNotHaveDoubleSpace",
        "severity": "critical"
      },
      "severity": "critical",
      "type": "expect_column_values_to_not_have_double_space"
    },
    {
      "id": "06cd5b51-510d-4cf7-99aa-f159acab7d74",
      "kwargs": {
        "column": "companyphone2",
        "result_format": {
          "result_format": "COMPLETE",
          "return_unexpected_rows": true
        }
      },
      "meta": {
        "dimension": "completeness",
        "name": "companyphone2-ExpectColumnValuesToNotBeNull",
        "severity": "critical"
      },
      "severity": "critical",
      "type": "expect_column_values_to_not_be_null"
    },
    {
      "id": "b00fd909-99c6-4553-9245-43f7aae2357f",
      "kwargs": {
        "column": "companyphone2",
        "result_format": {
          "result_format": "COMPLETE",
          "return_unexpected_rows": true
        }
      },
      "meta": {
        "dimension": "correctness",
        "name": "companyphone2-ExpectColumnValuesToMatchIndonesianPhoneRules",
        "severity": "warning"
      },
      "severity": "critical",
      "type": "expect_column_values_to_match_indonesian_phone_rules"
    },
    {
      "id": "fa0c9f6c-41f1-4f1c-9b4c-521674303f8b",
      "kwargs": {
        "column": "email",
        "result_format": {
          "result_format": "COMPLETE",
          "return_unexpected_rows": true
        }
      },
      "meta": {
        "dimension": "correctness",
        "name": "email-ExpectColumnValuesToNotHaveDoubleSpace",
        "severity": "critical"
      },
      "severity": "critical",
      "type": "expect_column_values_to_not_have_double_space"
    },
    {
      "id": "aa4790eb-f112-4dab-87e0-e8c1aa24c5cd",
      "kwargs": {
        "column": "email",
        "result_format": {
          "result_format": "COMPLETE",
          "return_unexpected_rows": true
        }
      },
      "meta": {
        "dimension": "completeness",
        "name": "email-ExpectColumnValuesToNotBeNull",
        "severity": "critical"
      },
      "severity": "critical",
      "type": "expect_column_values_to_not_be_null"
    },
    {
      "id": "4f481ea8-6994-49f2-ba6d-f952ad586d0b",
      "kwargs": {
        "column": "email",
        "result_format": {
          "result_format": "COMPLETE",
          "return_unexpected_rows": true
        }
      },
      "meta": {
        "dimension": "correctness",
        "name": "email-ExpectColumnValuesToBeEmail",
        "severity": "warning"
      },
      "severity": "critical",
      "type": "expect_column_values_to_be_email"
    },
    {
      "id": "8dafc547-186d-4b5d-9b7d-01dd46abb71e",
      "kwargs": {
        "column": "assetcategory",
        "result_format": {
          "result_format": "COMPLETE",
          "return_unexpected_rows": true
        }
      },
      "meta": {
        "dimension": "correctness",
        "name": "assetcategory-ExpectColumnValuesToNotHaveDoubleSpace",
        "severity": "critical"
      },
      "severity": "critical",
      "type": "expect_column_values_to_not_have_double_space"
    },
    {
      "id": "7e1c821f-7a8a-49b6-bb3d-86aba85d9e85",
      "kwargs": {
        "column": "assetcategory",
        "result_format": {
          "result_format": "COMPLETE",
          "return_unexpected_rows": true
        }
      },
      "meta": {
        "dimension": "completeness",
        "name": "assetcategory-ExpectColumnValuesToNotBeNull",
        "severity": "critical"
      },
      "severity": "critical",
      "type": "expect_column_values_to_not_be_null"
    },
    {
      "id": "d88c9a4a-e16a-4dae-903a-c0cf31d7ce33",
      "kwargs": {
        "column": "grading",
        "result_format": {
          "result_format": "COMPLETE",
          "return_unexpected_rows": true
        }
      },
      "meta": {
        "dimension": "correctness",
        "name": "grading-ExpectColumnValuesToNotHaveDoubleSpace",
        "severity": "critical"
      },
      "severity": "critical",
      "type": "expect_column_values_to_not_have_double_space"
    },
    {
      "id": "c8eee445-4ebd-4b4a-bb21-4a5364156f9f",
      "kwargs": {
        "column": "grading",
        "result_format": {
          "result_format": "COMPLETE",
          "return_unexpected_rows": true
        }
      },
      "meta": {
        "dimension": "completeness",
        "name": "grading-ExpectColumnValuesToNotBeNull",
        "severity": "critical"
      },
      "severity": "critical",
      "type": "expect_column_values_to_not_be_null"
    },
    {
      "id": "b3ac2619-4b04-40da-8e1c-86fdd529ab01",
      "kwargs": {
        "column": "rating",
        "result_format": {
          "result_format": "COMPLETE",
          "return_unexpected_rows": true
        }
      },
      "meta": {
        "dimension": "correctness",
        "name": "rating-ExpectColumnValuesToNotHaveDoubleSpace",
        "severity": "critical"
      },
      "severity": "critical",
      "type": "expect_column_values_to_not_have_double_space"
    },
    {
      "id": "a2c589b7-2d68-4bef-855a-e58bfcd2ce90",
      "kwargs": {
        "column": "rating",
        "result_format": {
          "result_format": "COMPLETE",
          "return_unexpected_rows": true
        }
      },
      "meta": {
        "dimension": "completeness",
        "name": "rating-ExpectColumnValuesToNotBeNull",
        "severity": "critical"
      },
      "severity": "critical",
      "type": "expect_column_values_to_not_be_null"
    },
    {
      "id": "8b870b32-3e20-4f39-80ee-304390f9019b",
      "kwargs": {
        "column": "collectortype",
        "result_format": {
          "result_format": "COMPLETE",
          "return_unexpected_rows": true
        }
      },
      "meta": {
        "dimension": "correctness",
        "name": "collectortype-ExpectColumnValuesToNotHaveDoubleSpace",
        "severity": "critical"
      },
      "severity": "critical",
      "type": "expect_column_values_to_not_have_double_space"
    },
    {
      "id": "aa18c93d-4911-4249-b109-988bca127d68",
      "kwargs": {
        "column": "collectortype",
        "result_format": {
          "result_format": "COMPLETE",
          "return_unexpected_rows": true
        }
      },
      "meta": {
        "dimension": "completeness",
        "name": "collectortype-ExpectColumnValuesToNotBeNull",
        "severity": "critical"
      },
      "severity": "critical",
      "type": "expect_column_values_to_not_be_null"
    },
    {
      "id": "5771dd8c-b6fa-42a6-be25-5299d3d0f6a9",
      "kwargs": {
        "column": "pdcduedate",
        "result_format": {
          "result_format": "COMPLETE",
          "return_unexpected_rows": true
        }
      },
      "meta": {
        "dimension": "correctness",
        "name": "pdcduedate-ExpectColumnValuesToNotHaveDoubleSpace",
        "severity": "critical"
      },
      "severity": "critical",
      "type": "expect_column_values_to_not_have_double_space"
    },
    {
      "id": "4420b1ed-fcb9-42dc-918e-3ff37eb3c39b",
      "kwargs": {
        "column": "pdcduedate",
        "result_format": {
          "result_format": "COMPLETE",
          "return_unexpected_rows": true
        }
      },
      "meta": {
        "dimension": "completeness",
        "name": "pdcduedate-ExpectColumnValuesToNotBeNull",
        "severity": "critical"
      },
      "severity": "critical",
      "type": "expect_column_values_to_not_be_null"
    },
    {
      "id": "45fbeeea-a318-47c2-8bf6-2afde89f755a",
      "kwargs": {
        "column": "pt",
        "result_format": {
          "result_format": "COMPLETE",
          "return_unexpected_rows": true
        }
      },
      "meta": {
        "dimension": "correctness",
        "name": "pt-ExpectColumnValuesToNotHaveDoubleSpace",
        "severity": "critical"
      },
      "severity": "critical",
      "type": "expect_column_values_to_not_have_double_space"
    },
    {
      "id": "beb335f0-aae8-4fd9-a068-1dc1a82f9b30",
      "kwargs": {
        "column": "pt",
        "result_format": {
          "result_format": "COMPLETE",
          "return_unexpected_rows": true
        }
      },
      "meta": {
        "dimension": "completeness",
        "name": "pt-ExpectColumnValuesToNotBeNull",
        "severity": "critical"
      },
      "severity": "critical",
      "type": "expect_column_values_to_not_be_null"
    }
  ],
  "id": "369d8b9f-95b0-4348-aad2-b407d3d3ce38",
  "meta": {
    "great_expectations_version": "1.12.3"
  },
  "name": "odps_dbo_collection__agreement_juris_masking_suite",
  "notes": null
}